blnuhr/LICENSE
blnuhr/__init__.py
blnuhr/_version.py
blnuhr/main.py
blnuhr/resources.py
blnuhr/resources/blnuhr.ui
blnuhr-0.1.13.dist-info/METADATA
blnuhr-0.1.13.dist-info/WHEEL
blnuhr-0.1.13.dist-info/entry_points.txt
blnuhr-0.1.13.dist-info/top_level.txt
blnuhr-0.1.13.dist-info/RECORD
