Metadata-Version: 2.1
Name: blnuhr
Version: 0.1.13
Summary: Python & Qt rendition of Berlin's quantity didactics clock
Home-page: https://github.com/prjemian/blnuhr/
Author: Pete R. Jemian
Author-email: prjemian@gmail.com
License: OPEN SOURCE LICENSE
Download-URL: https://github.com/prjemian/blnuhr/
Keywords: Python,Qt5,clock
Platform: any
Classifier: Development Status :: 4 - Beta
Classifier: Environment :: Console
Classifier: Environment :: Web Environment
Classifier: Intended Audience :: Science/Research
Classifier: License :: Free To Use But Restricted
Classifier: Operating System :: OS Independent
Classifier: Programming Language :: Python
Classifier: Topic :: Software Development :: Libraries :: Python Modules
Classifier: Topic :: Utilities
